Metadata-Version: 2.1
Name: django_remote_jsonschema_forms
Version: 1.0.1
Summary: A platform independent form serializer for Django.
Home-page: https://github.com/codesyntax/django_remote_jsonschema_forms
Author: Gorka Garcia
Author-email: ggarcia@codesyntax.com
Keywords: jsonschema,react,django,python
Classifier: Development Status :: 5 - Production/Stable
Classifier: Environment :: Web Environment
Classifier: Framework :: Django
Classifier: License :: OSI Approved :: MIT License
Classifier: Intended Audience :: Developers
Classifier: Operating System :: OS Independent
Classifier: Programming Language :: Python
Classifier: Programming Language :: Python :: 3.9
Classifier: Programming Language :: Python :: 3.10
Classifier: Programming Language :: Python :: 3.11
Classifier: Topic :: Utilities
Requires-Python: >=3.9
License-File: LICENSE
